README.rst
setup.py
hub_shim.egg-info/PKG-INFO
hub_shim.egg-info/SOURCES.txt
hub_shim.egg-info/dependency_links.txt
hub_shim.egg-info/not-zip-safe
hub_shim.egg-info/top_level.txt
otreehub/__init__.py
otreehub/apps.py
otreehub/models.py
otreehub/signals.py
otreehub/migrations/0001_initial.py
otreehub/migrations/0002_profile_user.py
otreehub/migrations/__init__.py