Metadata-Version: 1.0
Name: hub-shim
Version: 0.3.2
Summary: Shim package
Home-page: http://www.otree.org
Author: Chris
Author-email: chris@otree.org
License: MIT
Platform: UNKNOWN
